{
  "title": {
    "Japan": 0.0398,
    "Spain": 0.1379,
    "Norway": 0.0299,
    "Portugal": 0.0584,
    "Canada": 0.0092,
    "Belgium": 0.0264,
    "Colombia": 0.0372,
    "England": 0.0777,
    "Switzerland": 0.0187,
    "Ecuador": 0.0259,
    "France": 0.0778,
    "Iran": 0.0112,
    "Argentina": 0.1518,
    "Brazil": 0.0464,
    "South Korea": 0.0072,
    "Uruguay": 0.018,
    "Germany": 0.0298,
    "Morocco": 0.0236,
    "Mexico": 0.0159,
    "Turkey": 0.0176,
    "Scotland": 0.0039,
    "Netherlands": 0.0358,
    "Algeria": 0.0081,
    "Saudi Arabia": 0.0005,
    "Tunisia": 0.0004,
    "Austria": 0.0114,
    "Croatia": 0.0184,
    "Senegal": 0.0223,
    "Australia": 0.0065,
    "Czechia": 0.0044,
    "New Zealand": 0.0003,
    "Sweden": 0.0016,
    "Ivory Coast": 0.0053,
    "Paraguay": 0.0045,
    "Egypt": 0.0033,
    "South Africa": 0.0008,
    "Uzbekistan": 0.0019,
    "Bosnia and Herzegovina": 0.0007,
    "Panama": 0.0023,
    "United States": 0.0023,
    "Qatar": 0.0002,
    "Jordan": 0.0006,
    "DR Congo": 0.0014,
    "Curacao": 0.0002,
    "Ghana": 0.0001,
    "Haiti": 0.0008,
    "Iraq": 0.0011,
    "Cape Verde": 0.0005
  },
  "group_win": {
    "Mexico": 0.4369,
    "Canada": 0.36,
    "Morocco": 0.3412,
    "United States": 0.1515,
    "Germany": 0.4183,
    "Japan": 0.4465,
    "Iran": 0.2922,
    "Spain": 0.6919,
    "France": 0.4691,
    "Algeria": 0.1375,
    "Portugal": 0.4517,
    "Croatia": 0.2822,
    "Switzerland": 0.5125,
    "Brazil": 0.4825,
    "Australia": 0.2468,
    "Ecuador": 0.379,
    "Belgium": 0.4847,
    "Norway": 0.277,
    "Colombia": 0.3808,
    "South Korea": 0.2777,
    "Scotland": 0.1254,
    "Argentina": 0.661,
    "England": 0.5954,
    "Turkey": 0.3923,
    "Netherlands": 0.4201,
    "Senegal": 0.2163,
    "New Zealand": 0.0628,
    "Jordan": 0.0446,
    "Paraguay": 0.2094,
    "Tunisia": 0.0621,
    "Czechia": 0.2256,
    "Ivory Coast": 0.1674,
    "Bosnia and Herzegovina": 0.0858,
    "Haiti": 0.0509,
    "DR Congo": 0.0702,
    "South Africa": 0.0598,
    "Egypt": 0.1603,
    "Austria": 0.1569,
    "Uzbekistan": 0.0973,
    "Sweden": 0.0713,
    "Qatar": 0.0417,
    "Uruguay": 0.2212,
    "Saudi Arabia": 0.0424,
    "Iraq": 0.0376,
    "Cape Verde": 0.0445,
    "Panama": 0.095,
    "Ghana": 0.0274,
    "Curacao": 0.0353
  },
  "advance": {
    "Mexico": 0.8628,
    "South Korea": 0.7735,
    "Canada": 0.8829,
    "Switzerland": 0.927,
    "Morocco": 0.8455,
    "Brazil": 0.8991,
    "United States": 0.56,
    "Turkey": 0.8181,
    "Germany": 0.8829,
    "Ivory Coast": 0.6914,
    "Japan": 0.9022,
    "Netherlands": 0.883,
    "Iran": 0.7884,
    "Belgium": 0.892,
    "Spain": 0.9679,
    "Uruguay": 0.8314,
    "France": 0.8976,
    "Norway": 0.7901,
    "Algeria": 0.6582,
    "Austria": 0.6997,
    "Portugal": 0.8901,
    "Uzbekistan": 0.4958,
    "Croatia": 0.8449,
    "England": 0.951,
    "Egypt": 0.6433,
    "Argentina": 0.9582,
    "Paraguay": 0.6547,
    "Iraq": 0.2606,
    "Ecuador": 0.8723,
    "Colombia": 0.8574,
    "Bosnia and Herzegovina": 0.5241,
    "Saudi Arabia": 0.3802,
    "Czechia": 0.714,
    "Scotland": 0.5864,
    "Australia": 0.6945,
    "Tunisia": 0.4039,
    "Panama": 0.5833,
    "South Africa": 0.3486,
    "New Zealand": 0.3578,
    "Qatar": 0.3112,
    "Cape Verde": 0.4025,
    "Sweden": 0.456,
    "Senegal": 0.748,
    "Haiti": 0.3499,
    "Jordan": 0.3309,
    "DR Congo": 0.4159,
    "Ghana": 0.2544,
    "Curacao": 0.2564
  },
  "reach_r16": {
    "South Korea": 0.3905,
    "Germany": 0.5113,
    "Japan": 0.5211,
    "Morocco": 0.441,
    "France": 0.6118,
    "Ivory Coast": 0.2871,
    "Saudi Arabia": 0.0935,
    "Croatia": 0.4276,
    "Bosnia and Herzegovina": 0.1565,
    "Iran": 0.4046,
    "England": 0.6169,
    "Spain": 0.6419,
    "Ecuador": 0.4873,
    "Algeria": 0.2788,
    "Portugal": 0.5676,
    "Belgium": 0.5468,
    "Czechia": 0.3285,
    "United States": 0.2307,
    "Scotland": 0.2199,
    "Brazil": 0.5208,
    "Norway": 0.4743,
    "Netherlands": 0.5007,
    "Qatar": 0.0798,
    "Sweden": 0.1568,
    "Senegal": 0.4303,
    "Argentina": 0.6479,
    "Turkey": 0.4679,
    "Paraguay": 0.2961,
    "Haiti": 0.1035,
    "Mexico": 0.4861,
    "Uzbekistan": 0.1894,
    "Jordan": 0.0993,
    "Switzerland": 0.5245,
    "Uruguay": 0.3595,
    "Tunisia": 0.1268,
    "Canada": 0.4544,
    "Australia": 0.3407,
    "New Zealand": 0.1129,
    "DR Congo": 0.1477,
    "Colombia": 0.5098,
    "Egypt": 0.277,
    "Curacao": 0.0632,
    "Austria": 0.3007,
    "Iraq": 0.0879,
    "Ghana": 0.0597,
    "Cape Verde": 0.1028,
    "Panama": 0.2042,
    "South Africa": 0.1119
  },
  "reach_qf": {
    "Germany": 0.2575,
    "Japan": 0.3116,
    "Ivory Coast": 0.113,
    "Croatia": 0.2085,
    "Iran": 0.1727,
    "Spain": 0.4497,
    "Algeria": 0.1336,
    "Portugal": 0.3386,
    "Scotland": 0.0891,
    "Brazil": 0.3061,
    "Norway": 0.2567,
    "Netherlands": 0.3,
    "Belgium": 0.2913,
    "England": 0.3886,
    "Czechia": 0.121,
    "Ecuador": 0.2445,
    "Morocco": 0.2385,
    "Argentina": 0.4835,
    "Turkey": 0.2217,
    "South Korea": 0.1559,
    "Paraguay": 0.1183,
    "Mexico": 0.2264,
    "Uruguay": 0.1887,
    "Tunisia": 0.0407,
    "Australia": 0.1394,
    "France": 0.3935,
    "Canada": 0.1839,
    "Senegal": 0.2231,
    "Egypt": 0.1017,
    "Curacao": 0.0177,
    "Colombia": 0.2801,
    "Switzerland": 0.2438,
    "Iraq": 0.0258,
    "Haiti": 0.0327,
    "DR Congo": 0.0507,
    "New Zealand": 0.0305,
    "Austria": 0.1517,
    "Panama": 0.0725,
    "Qatar": 0.0165,
    "Jordan": 0.034,
    "Saudi Arabia": 0.0264,
    "Sweden": 0.0546,
    "Cape Verde": 0.0306,
    "United States": 0.0821,
    "Uzbekistan": 0.069,
    "South Africa": 0.031,
    "Bosnia and Herzegovina": 0.0396,
    "Ghana": 0.0129
  },
  "reach_sf": {
    "Japan": 0.1663,
    "Ivory Coast": 0.0427,
    "Spain": 0.3185,
    "Portugal": 0.1952,
    "Brazil": 0.1718,
    "Norway": 0.1333,
    "Iran": 0.071,
    "Morocco": 0.1171,
    "Turkey": 0.0928,
    "Paraguay": 0.0434,
    "Belgium": 0.1321,
    "Ecuador": 0.1253,
    "Australia": 0.0554,
    "France": 0.2446,
    "England": 0.2367,
    "Argentina": 0.3449,
    "Canada": 0.0736,
    "Germany": 0.1372,
    "Algeria": 0.0552,
    "Netherlands": 0.155,
    "Colombia": 0.1479,
    "Switzerland": 0.1037,
    "Croatia": 0.1041,
    "Haiti": 0.0076,
    "Egypt": 0.0355,
    "DR Congo": 0.017,
    "Panama": 0.0236,
    "South Korea": 0.0585,
    "Jordan": 0.0097,
    "Senegal": 0.1108,
    "New Zealand": 0.0082,
    "Scotland": 0.0308,
    "Uruguay": 0.0898,
    "Mexico": 0.0984,
    "Uzbekistan": 0.0273,
    "Saudi Arabia": 0.0076,
    "Czechia": 0.0416,
    "Tunisia": 0.0114,
    "Iraq": 0.0077,
    "Austria": 0.0659,
    "South Africa": 0.0083,
    "Bosnia and Herzegovina": 0.0098,
    "Sweden": 0.0172,
    "United States": 0.0257,
    "Cape Verde": 0.0084,
    "Ghana": 0.003,
    "Curacao": 0.0049,
    "Qatar": 0.0035
  },
  "reach_final": {
    "Japan": 0.0838,
    "Ivory Coast": 0.0134,
    "Spain": 0.2164,
    "Iran": 0.0283,
    "Norway": 0.0613,
    "Morocco": 0.0536,
    "Belgium": 0.0639,
    "Ecuador": 0.0599,
    "Portugal": 0.1101,
    "Argentina": 0.2304,
    "Canada": 0.0269,
    "Germany": 0.0669,
    "Colombia": 0.0766,
    "England": 0.1345,
    "Switzerland": 0.044,
    "Croatia": 0.048,
    "France": 0.1377,
    "DR Congo": 0.0053,
    "Panama": 0.0074,
    "Jordan": 0.0029,
    "Brazil": 0.0889,
    "Netherlands": 0.0724,
    "South Korea": 0.0205,
    "Uruguay": 0.042,
    "Turkey": 0.0437,
    "Mexico": 0.041,
    "Algeria": 0.0238,
    "Scotland": 0.011,
    "Saudi Arabia": 0.0022,
    "Tunisia": 0.0036,
    "Austria": 0.0267,
    "Czechia": 0.0135,
    "Egypt": 0.0129,
    "Senegal": 0.0513,
    "Australia": 0.0206,
    "Paraguay": 0.0159,
    "Uzbekistan": 0.0092,
    "Bosnia and Herzegovina": 0.0025,
    "Sweden": 0.0051,
    "New Zealand": 0.0016,
    "United States": 0.0083,
    "Haiti": 0.0026,
    "South Africa": 0.0021,
    "Ghana": 0.0007,
    "Qatar": 0.0011,
    "Cape Verde": 0.0022,
    "Iraq": 0.0025,
    "Curacao": 0.0008
  },
  "n_sims": 10000
}